{
  "main": {
    "id": "4e94a5ce2bbe1b7e",
    "type": "split",
    "children": [
      {
        "id": "9eafa5cebf222f87",
        "type": "tabs",
        "children": [
          {
            "id": "71652b7a07bb3cc8",
            "type": "leaf",
            "pane-relief:history-v1": {
              "pos": 1,
              "stack": [
                {
                  "title": "ANS Study",
                  "icon": "lucide-file",
                  "state": "{\"type\":\"markdown\",\"state\":{\"file\":\"ANS Study.md\",\"mode\":\"source\",\"source\":false},\"icon\":\"lucide-file\",\"title\":\"ANS Study\"}",
                  "eState": "{\"cursor\":{\"from\":{\"line\":0,\"ch\":0},\"to\":{\"line\":0,\"ch\":0}}}"
                },
                {
                  "state": "{}",
                  "eState": "{}"
                },
                {
                  "title": "0. Index",
                  "icon": "lucide-file",
                  "state": "{\"type\":\"markdown\",\"state\":{\"file\":\"0. Index.md\",\"mode\":\"source\",\"source\":false},\"icon\":\"lucide-file\",\"title\":\"0. Index\"}",
                  "eState": "{\"cursor\":{\"from\":{\"line\":10,\"ch\":17},\"to\":{\"line\":10,\"ch\":17}}}"
                }
              ]
            },
            "state": {
              "type": "markdown",
              "state": {
                "file": "10. AWS Direct Connect (DX).md",
                "mode": "source",
                "source": false
              },
              "icon": "lucide-file",
              "title": "10. AWS Direct Connect (DX)"
            }
          }
        ]
      }
    ],
    "direction": "vertical"
  },
  "left": {
    "id": "04638e4bf3480bc4",
    "type": "split",
    "children": [
      {
        "id": "eaf19dd8973095ff",
        "type": "tabs",
        "children": [
          {
            "id": "acf66450a02d42c5",
            "type": "leaf",
            "pane-relief:history-v1": {
              "pos": 0,
              "stack": [
                {
                  "state": "{}",
                  "eState": "{}"
                }
              ]
            },
            "state": {
              "type": "file-explorer",
              "state": {
                "sortOrder": "alphabetical",
                "autoReveal": false
              },
              "icon": "lucide-folder-closed",
              "title": "파일 탐색기"
            }
          },
          {
            "id": "0d7fef4892474e3d",
            "type": "leaf",
            "pane-relief:history-v1": {
              "pos": 0,
              "stack": [
                {
                  "state": "{}",
                  "eState": "{}"
                }
              ]
            },
            "state": {
              "type": "search",
              "state": {
                "query": "",
                "matchingCase": false,
                "explainSearch": false,
                "collapseAll": false,
                "extraContext": false,
                "sortOrder": "alphabetical"
              },
              "icon": "lucide-search",
              "title": "검색"
            }
          },
          {
            "id": "83a8c7716262993c",
            "type": "leaf",
            "pane-relief:history-v1": {
              "pos": 0,
              "stack": [
                {
                  "state": "{}",
                  "eState": "{}"
                }
              ]
            },
            "state": {
              "type": "bookmarks",
              "state": {},
              "icon": "lucide-bookmark",
              "title": "Bookmarks"
            }
          }
        ]
      }
    ],
    "direction": "horizontal",
    "width": 200
  },
  "right": {
    "id": "0934c8c665c2bfbf",
    "type": "split",
    "children": [
      {
        "id": "a475cca292bb4ac6",
        "type": "tabs",
        "children": [
          {
            "id": "cd51cc17a6449ef0",
            "type": "leaf",
            "pane-relief:history-v1": {
              "pos": 0,
              "stack": [
                {
                  "state": "{}",
                  "eState": "{}"
                }
              ]
            },
            "state": {
              "type": "backlink",
              "state": {
                "file": "ans_md.md",
                "collapseAll": false,
                "extraContext": false,
                "sortOrder": "alphabetical",
                "showSearch": false,
                "searchQuery": "",
                "backlinkCollapsed": false,
                "unlinkedCollapsed": true
              },
              "icon": "links-coming-in",
              "title": "ans_md의 백링크"
            }
          },
          {
            "id": "3edbf27bb808c35d",
            "type": "leaf",
            "pane-relief:history-v1": {
              "pos": 0,
              "stack": [
                {
                  "state": "{}",
                  "eState": "{}"
                }
              ]
            },
            "state": {
              "type": "outgoing-link",
              "state": {
                "file": "ans_md.md",
                "linksCollapsed": false,
                "unlinkedCollapsed": true
              },
              "icon": "links-going-out",
              "title": "ans_md의 나가는 링크"
            }
          },
          {
            "id": "907373e7f9cda147",
            "type": "leaf",
            "pane-relief:history-v1": {
              "pos": 0,
              "stack": [
                {
                  "state": "{}",
                  "eState": "{}"
                }
              ]
            },
            "state": {
              "type": "tag",
              "state": {
                "sortOrder": "frequency",
                "useHierarchy": true
              },
              "icon": "lucide-tags",
              "title": "Tags"
            }
          },
          {
            "id": "3a93a7297e45d167",
            "type": "leaf",
            "pane-relief:history-v1": {
              "pos": 0,
              "stack": [
                {
                  "state": "{}",
                  "eState": "{}"
                }
              ]
            },
            "state": {
              "type": "outline",
              "state": {
                "file": "ans_md.md"
              },
              "icon": "lucide-list",
              "title": "ans_md 개요"
            }
          },
          {
            "id": "79e32813581d4c04",
            "type": "leaf",
            "pane-relief:history-v1": {
              "pos": 0,
              "stack": [
                {
                  "state": "{}",
                  "eState": "{}"
                }
              ]
            },
            "state": {
              "type": "git-view",
              "state": {},
              "icon": "git-pull-request",
              "title": "Source Control"
            }
          }
        ],
        "currentTab": 4
      }
    ],
    "direction": "horizontal",
    "width": 300
  },
  "left-ribbon": {
    "hiddenItems": {
      "switcher:빠른 전환기 열기": false,
      "daily-notes:오늘의 일일 노트 열기": false,
      "graph:그래프 뷰 열기": false,
      "canvas:새 캔버스 만들기": false,
      "templates:템플릿 삽입": false,
      "command-palette:명령어 팔레트 열기": false,
      "obsidian-git:Open Git source control": false
    }
  },
  "active": "acf66450a02d42c5",
  "lastOpenFiles": [
    "ANS Study.md",
    "10. AWS Direct Connect (DX).md",
    "image/Pasted image 20250207183637.png",
    "0. Index.md",
    "8. Transit Gateway.md",
    "4. Network Performance and Optimization.md",
    "9. Hybrid Network Basic.md",
    "7. VPC Interface Endpoint and PrivateLink.md",
    "6. VPC Gateway Endpoint.md",
    "5. VPC Peering.md",
    "3. VPC DNS and DHCP.md",
    "1. Amazon VPC Fundamentals.md",
    "2. Additionnal VPC Feature.md",
    "image/Pasted image 20250207175318.png",
    "image/Pasted image 20250207175340.png",
    "image/Pasted image 20250207162806.png",
    "image/Pasted image 20250207174410.png",
    "image/Pasted image 20250207174400.png",
    "image/Pasted image 20250207173745.png",
    "image/Pasted image 20250207173046.png",
    "image/Pasted image 20250207173034.png",
    "image/Pasted image 20250207172730.png",
    "image",
    "Welcome.md"
  ]
}